nose_checker.py
setup.py
pylint_nose_checker.egg-info/PKG-INFO
pylint_nose_checker.egg-info/SOURCES.txt
pylint_nose_checker.egg-info/dependency_links.txt
pylint_nose_checker.egg-info/requires.txt
pylint_nose_checker.egg-info/top_level.txt