Metadata-Version: 1.0
Name: pylint-nose-checker
Version: 1.0.0
Summary: A pylint plugin which fixes nose.tools import errors
Home-page: http://github.com/OddBloke/pylint-nose-checker
Author: Daniel Watkins
Author-email: daniel@daniel-watkins.co.uk
License: GPLv3
Platform: UNKNOWN
